[
  {
    "name": "श्रीकृष्ण",
    "description": "भगवान विष्णु के अवतार, अर्जुन के सारथी और गीता के उपदेशक।",
    "imageName": "krishna"
  },
  {
    "name": "अर्जुन",
    "description": "पाण्डवों के श्रेष्ठ धनुर्धर, जिनके मोह को दूर करने के लिए गीता का उपदेश दिया गया।",
    "imageName": "arjuna"
  },
  {
    "name": "संजय",
    "description": "धृतराष्ट्र के सारथी, जिन्होंने कुरुक्षेत्र युद्ध का वर्णन किया।",
    "imageName": "sanjay"
  },
  {
    "name": "धृतराष्ट्र",
    "description": "कौरवों के पिता, जन्म से अंधे राजा।",
    "imageName": "dhritarashtra"
  }
]
